py3mf_slicer/__init__.py
py3mf_slicer/get_items.py
py3mf_slicer/load.py
py3mf_slicer/slice.py
py3mf_slicer/transform.py
py3mf_slicer/visualize.py
py3mf_slicer/write.py
py3mf_slicer-0.0.5.dist-info/licenses/LICENSE
tests/__init__.py
tests/test_complex_geometry.py
tests/test_module1.py
tests/test_vis.py
py3mf_slicer-0.0.5.dist-info/METADATA
py3mf_slicer-0.0.5.dist-info/WHEEL
py3mf_slicer-0.0.5.dist-info/top_level.txt
py3mf_slicer-0.0.5.dist-info/RECORD
