Metadata-Version: 2.4
Name: py3mf_slicer
Version: 0.0.5
Summary: Functions which aids the process of using and slicing 3mf files
Home-page: https://github.com/wiberganton/py3mf_slicer
Author: Anton Wiberg
Author-email: wiberg.anton@gmail.com
Classifier: Programming Language :: Python :: 3
Classifier: License :: OSI Approved :: MIT License
Classifier: Operating System :: OS Independent
Requires-Python: >=3.6
License-File: LICENSE
Requires-Dist: setuptools
Requires-Dist: lib3mf
Requires-Dist: pyvista
Requires-Dist: numpy
Requires-Dist: networkx
Requires-Dist: shapely
Dynamic: author
Dynamic: author-email
Dynamic: classifier
Dynamic: description
Dynamic: description-content-type
Dynamic: home-page
Dynamic: license-file
Dynamic: requires-dist
Dynamic: requires-python
Dynamic: summary
